oracledb_mcp_server/__init__.py
oracledb_mcp_server/__main__.py
oracledb_mcp_server/utils.py
orange_oracledb_mcp_server-0.1.0.dist-info/licenses/LICENSE
orange_oracledb_mcp_server-0.1.0.dist-info/METADATA
orange_oracledb_mcp_server-0.1.0.dist-info/WHEEL
orange_oracledb_mcp_server-0.1.0.dist-info/entry_points.txt
orange_oracledb_mcp_server-0.1.0.dist-info/top_level.txt
orange_oracledb_mcp_server-0.1.0.dist-info/RECORD
